setup.py
distributions_GaussBinom/Binomialdistribution.py
distributions_GaussBinom/Gaussiandistribution.py
distributions_GaussBinom/Generaldistribution.py
distributions_GaussBinom/__init__.py
distributions_GaussBinom.egg-info/PKG-INFO
distributions_GaussBinom.egg-info/SOURCES.txt
distributions_GaussBinom.egg-info/dependency_links.txt
distributions_GaussBinom.egg-info/not-zip-safe
distributions_GaussBinom.egg-info/top_level.txt