Metadata-Version: 1.0
Name: distributions-GaussBinom
Version: 1.1
Summary: Gaussian distributions and Binomial distributions
Home-page: UNKNOWN
Author: UNKNOWN
Author-email: UNKNOWN
License: UNKNOWN
Platform: UNKNOWN
